validated_chat/__init__.py
validated_chat-0.0.2.dist-info/LICENSE
validated_chat-0.0.2.dist-info/METADATA
validated_chat-0.0.2.dist-info/WHEEL
validated_chat-0.0.2.dist-info/top_level.txt
validated_chat-0.0.2.dist-info/RECORD
