Metadata-Version: 2.1
Name: validated_chat
Version: 0.0.2
Summary: A package to generate and validate chat responses with retry logic.
Author: Eugene Evstafev
Author-email: chigwel@gmail.com
Requires-Python: >=3.7
License-File: LICENSE
Requires-Dist: ollama==0.4.4
Requires-Dist: pydantic==2.10.3
